{
    "title":  "BAND-MAID YouTube Quiz",
    "description":  "Test your knowledge of BAND-MAID on YouTube.",
    "questions":  [
                      {
                          "id":  1,
                          "image":  "https://img.youtube.com/vi/vu2D3lzH7Y0/sddefault.jpg",
                          "question":  "Which of these BAND-MAID videos has the most total views on YouTube?",
                          "explanation":  "What is justice? — Views: 1,170,807 | Yesterday: 2,612\nREAL EXISTENCE — Views: 830,410 | Yesterday: 548\nDifferent — Views: 827,184 | Yesterday: 615",
                          "choices":  [
                                          {
                                              "text":  "What is justice?",
                                              "correct":  true
                                          },
                                          {
                                              "text":  "REAL EXISTENCE"
                                          },
                                          {
                                              "text":  "Different"
                                          }
                                      ]
                      }
                  ]
}
