{
    "title":  "BAND-MAID Song Quiz",
    "description":  "Test your knowledge of BAND-MAID songs.",
    "questions":  [
                      {
                          "id":  1,
                          "image":  "https://drivetimebm.github.io/BAND-MAID_gpt/photos/quiz.png",
                          "question":  "Which of these BAND-MAID songs has the most streams on Spotify?",
                          "explanation":  "Big Dad — Spotify: 734,615 | Played Live: 9\nTIME — Spotify: 730,870 | Played Live: 50\nPrice of Pride — Spotify: 696,316 | Played Live: 15",
                          "choices":  [
                                          {
                                              "text":  "Price of Pride"
                                          },
                                          {
                                              "text":  "TIME"
                                          },
                                          {
                                              "text":  "Big Dad",
                                              "correct":  true
                                          }
                                      ]
                      }
                  ]
}
