{
    "title":  "BAND-MAID Song Quiz",
    "description":  "Test your knowledge of BAND-MAID songs.",
    "questions":  [
                      {
                          "id":  1,
                          "image":  "https://drivetimebm.github.io/BAND-MAID_gpt/photos/quiz.png",
                          "question":  "Which of these BAND-MAID songs has been played live the most times?",
                          "explanation":  "Knockin\u0027 on your heart — Spotify: 698,318 | Played Live: 55\nTIME — Spotify: 729,003 | Played Live: 50\nBlooming — Spotify: 4,172,584 | Played Live: 44",
                          "choices":  [
                                          {
                                              "text":  "TIME"
                                          },
                                          {
                                              "text":  "Blooming"
                                          },
                                          {
                                              "text":  "Knockin\u0027 on your heart",
                                              "correct":  true
                                          }
                                      ]
                      }
                  ]
}
