{
    "title":  "BAND-MAID Song Quiz",
    "description":  "Test your knowledge of BAND-MAID songs.",
    "questions":  [
                      {
                          "id":  1,
                          "image":  "https://drivetimebm.github.io/BAND-MAID_gpt/photos/quiz.png",
                          "question":  "Which of these BAND-MAID songs has been played live the most times?",
                          "explanation":  "Unleash!!!!! — Spotify: 3,542,195 | Played Live: 101\nsecret My lips — Spotify: 1,817,930 | Played Live: 85\nHATE? — Spotify: 1,967,433 | Played Live: 78",
                          "choices":  [
                                          {
                                              "text":  "secret My lips"
                                          },
                                          {
                                              "text":  "HATE?"
                                          },
                                          {
                                              "text":  "Unleash!!!!!",
                                              "correct":  true
                                          }
                                      ]
                      }
                  ]
}
